pshell/__init__.py
pshell/client.py
pshell/plot.py
pshell/proxy.py
pshell/sse.py
psi_pshell-2.0.1.dist-info/METADATA
psi_pshell-2.0.1.dist-info/WHEEL
psi_pshell-2.0.1.dist-info/top_level.txt
psi_pshell-2.0.1.dist-info/RECORD
