Metadata-Version: 2.1
Name: psi-pshell
Version: 2.0.1
Summary: Python client to PShell REST API
Home-page: https://github.com/paulscherrerinstitute/pshell/tree/master/python
Author: Paul Scherrer Institute
Author-email: daq@psi.ch
License: GPLv3
Requires-Dist: requests
Requires-Dist: sseclient
Requires-Dist: pyzmq
